gbmpulsar/GBM_data_filter.py
gbmpulsar/GBM_pulsar_pipeline.py
gbmpulsar/__init__.py
gbmpulsar/barycor/__init__.py
gbmpulsar/barycor/barycor.py
gbmpulsar/barycor/tdb2tdt.py
gbmpulsar-0.1.5.dist-info/METADATA
gbmpulsar-0.1.5.dist-info/WHEEL
gbmpulsar-0.1.5.dist-info/entry_points.txt
gbmpulsar-0.1.5.dist-info/top_level.txt
gbmpulsar-0.1.5.dist-info/RECORD
