Metadata-Version: 2.1
Name: gbmpulsar
Version: 0.1.5
Summary: A GBM tool for X-ray pulsar analysis
Home-page: https://github.com/tuoyl/gbm-pulsar
Author: Youli Tuo
Author-email: tuoyl@ihep.ac.cn
License: MIT
Classifier: License :: OSI Approved :: MIT License
Classifier: Programming Language :: Python
Classifier: Programming Language :: Python :: 3
Classifier: Programming Language :: Python :: 3.6
Classifier: Programming Language :: Python :: Implementation :: CPython
Classifier: Programming Language :: Python :: Implementation :: PyPy
Requires-Python: >=3.6.0
Requires-Dist: numpy
Requires-Dist: astropy
Requires-Dist: requests
Requires-Dist: jsonschema
